{
  "exercise": "Incline Push-Up Medium",
  "states": {
    "start": {
      "angles": {
        "elbow_left": 132.4,
        "elbow_right": 74.79,
        "knee_left": 166.42,
        "knee_right": 167.14,
        "hip_left": 163.12,
        "hip_right": 177.99,
        "shoulder_left": 68.46,
        "shoulder_right": 33.05
      },
      "ratios": {
        "forearm_upperarm_left": 0.943,
        "forearm_upperarm_right": 0.761,
        "shin_thigh_left": 1.449,
        "shin_thigh_right": 1.493
      },
      "orientation": {
        "torso_tilt_deg": 66.0,
        "hip_shoulder_alignment_deg": 1.77
      },
      "landmarks": {
        "ordered_names": [
          "nose",
          "left_eye_inner",
          "left_eye",
          "left_eye_outer",
          "right_eye_inner",
          "right_eye",
          "right_eye_outer",
          "left_ear",
          "right_ear",
          "mouth_left",
          "mouth_right",
          "left_shoulder",
          "right_shoulder",
          "left_elbow",
          "right_elbow",
          "left_wrist",
          "right_wrist",
          "left_pinky",
          "right_pinky",
          "left_index",
          "right_index",
          "left_thumb",
          "right_thumb",
          "left_hip",
          "right_hip",
          "left_knee",
          "right_knee",
          "left_ankle",
          "right_ankle",
          "left_heel",
          "right_heel",
          "left_foot_index",
          "right_foot_index"
        ],
        "points": [
          {
            "x": 0.4018456041812897,
            "y": 0.12600331008434296,
            "z": -0.5125561356544495,
            "visibility": 0.9996053576469421
          },
          {
            "x": 0.4064406156539917,
            "y": 0.11202332377433777,
            "z": -0.5433139801025391,
            "visibility": 0.999314546585083
          },
          {
            "x": 0.4123273193836212,
            "y": 0.11095206439495087,
            "z": -0.5433375835418701,
            "visibility": 0.9993153810501099
          },
          {
            "x": 0.41866928339004517,
            "y": 0.10951055586338043,
            "z": -0.5434668660163879,
            "visibility": 0.9994064569473267
          },
          {
            "x": 0.39487895369529724,
            "y": 0.11226221919059753,
            "z": -0.49909335374832153,
            "visibility": 0.9989585876464844
          },
          {
            "x": 0.39229273796081543,
            "y": 0.11149442195892334,
            "z": -0.49919968843460083,
            "visibility": 0.998770534992218
          },
          {
            "x": 0.3896709382534027,
            "y": 0.11068200320005417,
            "z": -0.49932175874710083,
            "visibility": 0.9989100694656372
          },
          {
            "x": 0.44148918986320496,
            "y": 0.10383140295743942,
            "z": -0.5491793751716614,
            "visibility": 0.9993222951889038
          },
          {
            "x": 0.4026005268096924,
            "y": 0.10630735009908676,
            "z": -0.3528684675693512,
            "visibility": 0.9981208443641663
          },
          {
            "x": 0.4192335903644562,
            "y": 0.1350478231906891,
            "z": -0.5016688108444214,
            "visibility": 0.9997150301933289
          },
          {
            "x": 0.4054066240787506,
            "y": 0.13550534844398499,
            "z": -0.44510042667388916,
            "visibility": 0.999461829662323
          },
          {
            "x": 0.542819082736969,
            "y": 0.14109398424625397,
            "z": -0.5155457854270935,
            "visibility": 0.9999750852584839
          },
          {
            "x": 0.3835368752479553,
            "y": 0.1511285901069641,
            "z": -0.16573762893676758,
            "visibility": 0.9999288320541382
          },
          {
            "x": 0.5805138349533081,
            "y": 0.22467252612113953,
            "z": -0.5131010413169861,
            "visibility": 0.9971869587898254
          },
          {
            "x": 0.34656935930252075,
            "y": 0.2259519100189209,
            "z": -0.02826819382607937,
            "visibility": 0.9454516768455505
          },
          {
            "x": 0.568281352519989,
            "y": 0.29562485218048096,
            "z": -0.5610907077789307,
            "visibility": 0.9937213659286499
          },
          {
            "x": 0.3011758029460907,
            "y": 0.297222375869751,
            "z": -0.11682639271020889,
            "visibility": 0.9720044136047363
          },
          {
            "x": 0.5616722702980042,
            "y": 0.3171195983886719,
            "z": -0.6166540384292603,
            "visibility": 0.9838950037956238
          },
          {
            "x": 0.2766472101211548,
            "y": 0.3142974376678467,
            "z": -0.13561464846134186,
            "visibility": 0.9462054371833801
          },
          {
            "x": 0.5405532717704773,
            "y": 0.310352623462677,
            "z": -0.6332629323005676,
            "visibility": 0.9840542674064636
          },
          {
            "x": 0.27926838397979736,
            "y": 0.31512972712516785,
            "z": -0.19233177602291107,
            "visibility": 0.9528827667236328
          },
          {
            "x": 0.5399764776229858,
            "y": 0.3031386435031891,
            "z": -0.5652360320091248,
            "visibility": 0.9771480560302734
          },
          {
            "x": 0.29085707664489746,
            "y": 0.3110690116882324,
            "z": -0.14364369213581085,
            "visibility": 0.9518593549728394
          },
          {
            "x": 0.5692963600158691,
            "y": 0.29708731174468994,
            "z": -0.09740351885557175,
            "visibility": 0.9987561702728271
          },
          {
            "x": 0.4926215708255768,
            "y": 0.30430710315704346,
            "z": 0.0971982479095459,
            "visibility": 0.9982263445854187
          },
          {
            "x": 0.6132547855377197,
            "y": 0.4016927480697632,
            "z": 0.05602924898266792,
            "visibility": 0.697730541229248
          },
          {
            "x": 0.5657112002372742,
            "y": 0.3967577815055847,
            "z": 0.2556172311306,
            "visibility": 0.37136802077293396
          },
          {
            "x": 0.6572955846786499,
            "y": 0.49997764825820923,
            "z": 0.31070366501808167,
            "visibility": 0.6635001301765442
          },
          {
            "x": 0.6353186368942261,
            "y": 0.493491530418396,
            "z": 0.5251504182815552,
            "visibility": 0.3835222125053406
          },
          {
            "x": 0.678774356842041,
            "y": 0.5169909000396729,
            "z": 0.3307499587535858,
            "visibility": 0.6215500831604004
          },
          {
            "x": 0.6507896184921265,
            "y": 0.5059452652931213,
            "z": 0.5511966347694397,
            "visibility": 0.4096900224685669
          },
          {
            "x": 0.6417587399482727,
            "y": 0.5442570447921753,
            "z": 0.2070370316505432,
            "visibility": 0.6865465641021729
          },
          {
            "x": 0.6133680939674377,
            "y": 0.5307344198226929,
            "z": 0.4611164927482605,
            "visibility": 0.5308709144592285
          }
        ]
      }
    },
    "end": {
      "angles": {
        "elbow_left": 131.18,
        "elbow_right": 176.68,
        "knee_left": 173.75,
        "knee_right": 171.67,
        "hip_left": 172.29,
        "hip_right": 176.82,
        "shoulder_left": 31.08,
        "shoulder_right": 20.45
      },
      "ratios": {
        "forearm_upperarm_left": 0.811,
        "forearm_upperarm_right": 0.521,
        "shin_thigh_left": 1.039,
        "shin_thigh_right": 1.173
      },
      "orientation": {
        "torso_tilt_deg": 77.98,
        "hip_shoulder_alignment_deg": 6.05
      },
      "landmarks": {
        "ordered_names": [
          "nose",
          "left_eye_inner",
          "left_eye",
          "left_eye_outer",
          "right_eye_inner",
          "right_eye",
          "right_eye_outer",
          "left_ear",
          "right_ear",
          "mouth_left",
          "mouth_right",
          "left_shoulder",
          "right_shoulder",
          "left_elbow",
          "right_elbow",
          "left_wrist",
          "right_wrist",
          "left_pinky",
          "right_pinky",
          "left_index",
          "right_index",
          "left_thumb",
          "right_thumb",
          "left_hip",
          "right_hip",
          "left_knee",
          "right_knee",
          "left_ankle",
          "right_ankle",
          "left_heel",
          "right_heel",
          "left_foot_index",
          "right_foot_index"
        ],
        "points": [
          {
            "x": 0.3423846364021301,
            "y": 0.25999215245246887,
            "z": -0.7287498712539673,
            "visibility": 0.9996079802513123
          },
          {
            "x": 0.34253716468811035,
            "y": 0.2481691837310791,
            "z": -0.7608093023300171,
            "visibility": 0.9997913241386414
          },
          {
            "x": 0.3472124934196472,
            "y": 0.24587754905223846,
            "z": -0.7607320547103882,
            "visibility": 0.9997566342353821
          },
          {
            "x": 0.3517858684062958,
            "y": 0.24330702424049377,
            "z": -0.7610182762145996,
            "visibility": 0.9998377561569214
          },
          {
            "x": 0.3298693895339966,
            "y": 0.25051823258399963,
            "z": -0.7288654446601868,
            "visibility": 0.9994309544563293
          },
          {
            "x": 0.3258998394012451,
            "y": 0.24987800419330597,
            "z": -0.7289110422134399,
            "visibility": 0.9990653395652771
          },
          {
            "x": 0.3221955895423889,
            "y": 0.24896010756492615,
            "z": -0.7288094162940979,
            "visibility": 0.9992196559906006
          },
          {
            "x": 0.37040919065475464,
            "y": 0.22825582325458527,
            "z": -0.7439088225364685,
            "visibility": 0.999950647354126
          },
          {
            "x": 0.32868510484695435,
            "y": 0.23855184018611908,
            "z": -0.6013235449790955,
            "visibility": 0.9994524121284485
          },
          {
            "x": 0.3605058789253235,
            "y": 0.2616615891456604,
            "z": -0.7050081491470337,
            "visibility": 0.9997972846031189
          },
          {
            "x": 0.34445035457611084,
            "y": 0.2648206353187561,
            "z": -0.6641364693641663,
            "visibility": 0.9993147850036621
          },
          {
            "x": 0.48285531997680664,
            "y": 0.23097077012062073,
            "z": -0.5930347442626953,
            "visibility": 0.9999951124191284
          },
          {
            "x": 0.3364061117172241,
            "y": 0.24859902262687683,
            "z": -0.3611459732055664,
            "visibility": 0.9998732805252075
          },
          {
            "x": 0.6089940071105957,
            "y": 0.25103405117988586,
            "z": -0.4191271662712097,
            "visibility": 0.9993422627449036
          },
          {
            "x": 0.3126741647720337,
            "y": 0.2846762537956238,
            "z": -0.027008170261979103,
            "visibility": 0.7748380303382874
          },
          {
            "x": 0.5723446607589722,
            "y": 0.30030280351638794,
            "z": -0.2553297281265259,
            "visibility": 0.985729455947876
          },
          {
            "x": 0.2904829978942871,
            "y": 0.30581650137901306,
            "z": 0.14590993523597717,
            "visibility": 0.7027978897094727
          },
          {
            "x": 0.5636933445930481,
            "y": 0.3181149661540985,
            "z": -0.263626366853714,
            "visibility": 0.936476469039917
          },
          {
            "x": 0.2777983844280243,
            "y": 0.31450867652893066,
            "z": 0.16864287853240967,
            "visibility": 0.5846328735351562
          },
          {
            "x": 0.5409740805625916,
            "y": 0.31360772252082825,
            "z": -0.26830416917800903,
            "visibility": 0.9368562698364258
          },
          {
            "x": 0.2858518064022064,
            "y": 0.31143423914909363,
            "z": 0.1335950344800949,
            "visibility": 0.5983356237411499
          },
          {
            "x": 0.5384911894798279,
            "y": 0.3090818226337433,
            "z": -0.2481907606124878,
            "visibility": 0.9079889059066772
          },
          {
            "x": 0.29463309049606323,
            "y": 0.3089744448661804,
            "z": 0.13678085803985596,
            "visibility": 0.6141382455825806
          },
          {
            "x": 0.530215322971344,
            "y": 0.34252703189849854,
            "z": -0.07721266895532608,
            "visibility": 0.9996826648712158
          },
          {
            "x": 0.4609917402267456,
            "y": 0.34350889921188354,
            "z": 0.07751455157995224,
            "visibility": 0.9987792372703552
          },
          {
            "x": 0.5972439050674438,
            "y": 0.4248163104057312,
            "z": 0.22227729856967926,
            "visibility": 0.6532614231109619
          },
          {
            "x": 0.5467514991760254,
            "y": 0.4249771237373352,
            "z": 0.37115713953971863,
            "visibility": 0.2933349907398224
          },
          {
            "x": 0.6444815993309021,
            "y": 0.48409339785575867,
            "z": 0.5437124371528625,
            "visibility": 0.6892493963241577
          },
          {
            "x": 0.6144468784332275,
            "y": 0.48102954030036926,
            "z": 0.7319295406341553,
            "visibility": 0.4268363416194916
          },
          {
            "x": 0.6649200320243835,
            "y": 0.48872846364974976,
            "z": 0.5726450085639954,
            "visibility": 0.767402172088623
          },
          {
            "x": 0.6484463214874268,
            "y": 0.48771199584007263,
            "z": 0.7684704065322876,
            "visibility": 0.46239253878593445
          },
          {
            "x": 0.6295111775398254,
            "y": 0.5185081362724304,
            "z": 0.4732595384120941,
            "visibility": 0.7479060888290405
          },
          {
            "x": 0.6113150119781494,
            "y": 0.5207496285438538,
            "z": 0.6953916549682617,
            "visibility": 0.5746206641197205
          }
        ]
      }
    }
  },
  "rep_logic": "start -> end",
  "tolerance": {
    "angle_deg": 15,
    "ratio_pct": 0.15
  },
  "coco": {
    "start_keypoints": [
      0.4018456041812897,
      0.12600331008434296,
      0.9996053576469421,
      0.4123273193836212,
      0.11095206439495087,
      0.9993153810501099,
      0.39229273796081543,
      0.11149442195892334,
      0.998770534992218,
      0.44148918986320496,
      0.10383140295743942,
      0.9993222951889038,
      0.4026005268096924,
      0.10630735009908676,
      0.9981208443641663,
      0.542819082736969,
      0.14109398424625397,
      0.9999750852584839,
      0.3835368752479553,
      0.1511285901069641,
      0.9999288320541382,
      0.5805138349533081,
      0.22467252612113953,
      0.9971869587898254,
      0.34656935930252075,
      0.2259519100189209,
      0.9454516768455505,
      0.568281352519989,
      0.29562485218048096,
      0.9937213659286499,
      0.3011758029460907,
      0.297222375869751,
      0.9720044136047363,
      0.5692963600158691,
      0.29708731174468994,
      0.9987561702728271,
      0.4926215708255768,
      0.30430710315704346,
      0.9982263445854187,
      0.6132547855377197,
      0.4016927480697632,
      0.697730541229248,
      0.5657112002372742,
      0.3967577815055847,
      0.37136802077293396,
      0.6572955846786499,
      0.49997764825820923,
      0.6635001301765442,
      0.6353186368942261,
      0.493491530418396,
      0.3835222125053406
    ],
    "end_keypoints": [
      0.3423846364021301,
      0.25999215245246887,
      0.9996079802513123,
      0.3472124934196472,
      0.24587754905223846,
      0.9997566342353821,
      0.3258998394012451,
      0.24987800419330597,
      0.9990653395652771,
      0.37040919065475464,
      0.22825582325458527,
      0.999950647354126,
      0.32868510484695435,
      0.23855184018611908,
      0.9994524121284485,
      0.48285531997680664,
      0.23097077012062073,
      0.9999951124191284,
      0.3364061117172241,
      0.24859902262687683,
      0.9998732805252075,
      0.6089940071105957,
      0.25103405117988586,
      0.9993422627449036,
      0.3126741647720337,
      0.2846762537956238,
      0.7748380303382874,
      0.5723446607589722,
      0.30030280351638794,
      0.985729455947876,
      0.2904829978942871,
      0.30581650137901306,
      0.7027978897094727,
      0.530215322971344,
      0.34252703189849854,
      0.9996826648712158,
      0.4609917402267456,
      0.34350889921188354,
      0.9987792372703552,
      0.5972439050674438,
      0.4248163104057312,
      0.6532614231109619,
      0.5467514991760254,
      0.4249771237373352,
      0.2933349907398224,
      0.6444815993309021,
      0.48409339785575867,
      0.6892493963241577,
      0.6144468784332275,
      0.48102954030036926,
      0.4268363416194916
    ],
    "format": "coco-17-[x,y,visibility]*17 (normalized)"
  }
}